p2p_arcade/__init__.py
p2p_arcade/p2p_arcade.py
p2p_arcade-0.2.dist-info/LICENSE
p2p_arcade-0.2.dist-info/METADATA
p2p_arcade-0.2.dist-info/WHEEL
p2p_arcade-0.2.dist-info/entry_points.txt
p2p_arcade-0.2.dist-info/top_level.txt
p2p_arcade-0.2.dist-info/RECORD
