Metadata-Version: 2.1
Name: p2p-arcade
Version: 0.2
Summary: A Non-Blocking Event Driven Applications Framework
Home-page: https://github.com/MrYsLab/p2p-arcade
Author: Alan Yorinks
Author-email: MisterYsLab@gmail.com
License: GNU Affero General Public License v3 or later (AGPLv3+)
Keywords: arcade,p2p,games,arcade
Platform: UNKNOWN
Classifier: Development Status :: 4 - Beta
Classifier: Environment :: Other Environment
Classifier: Intended Audience :: Education
Classifier: Intended Audience :: Developers
Classifier: License :: OSI Approved :: GNU Affero General Public License v3 or later (AGPLv3+)
Classifier: Operating System :: OS Independent
Classifier: Programming Language :: Python :: 3.7
Classifier: Topic :: Education
Requires-Dist: arcade
Requires-Dist: msgpack
Requires-Dist: psutil
Requires-Dist: python-banyan
Requires-Dist: zmq
